abs_rbac_core/__init__.py
abs_rbac_core/decorator.py
abs_rbac_core/service.py
abs_rbac_core-0.1.9.dist-info/METADATA
abs_rbac_core-0.1.9.dist-info/WHEEL
abs_rbac_core-0.1.9.dist-info/RECORD
