Metadata-Version: 2.3
Name: abs-rbac-core
Version: 0.1.9
Summary: Core functionality of the RBAC services using the casbin and SQLAlchemy
License: MIT
Author: AutoBridgeSystems
Author-email: info@autobridgesystems.com
Requires-Python: >=3.13,<4.0
Classifier: License :: OSI Approved :: MIT License
Classifier: Programming Language :: Python :: 3
Classifier: Programming Language :: Python :: 3.13
Requires-Dist: abs-exception-core (>=0.1.0,<0.2.0)
Requires-Dist: casbin (>=1.41.0,<2.0.0)
Requires-Dist: casbin-sqlalchemy-adapter (>=1.4.0,<2.0.0)
Requires-Dist: fastapi[standard] (>=0.115.12,<0.116.0)
Requires-Dist: sqlalchemy (>=2.0.40,<3.0.0)
